classicmagedps/__init__.py
classicmagedps/env.py
classicmagedps/mage.py
classicmagedps/simulation.py
classicmagedps/utils.py
classicmagedps-0.3.2.dist-info/WHEEL
classicmagedps-0.3.2.dist-info/METADATA
classicmagedps-0.3.2.dist-info/RECORD
